odoo8_addon_partner_contact_address_detailed-8.0.1.0.0.99.dev11-py3.8-nspkg.pth
odoo_addons/partner_contact_address_detailed/__init__.py
odoo_addons/partner_contact_address_detailed/__openerp__.py
odoo_addons/partner_contact_address_detailed/partner_view.xml
odoo_addons/partner_contact_address_detailed/i18n/de.po
odoo_addons/partner_contact_address_detailed/i18n/es.po
odoo_addons/partner_contact_address_detailed/i18n/eu.po
odoo_addons/partner_contact_address_detailed/i18n/fi.po
odoo_addons/partner_contact_address_detailed/i18n/it.po
odoo_addons/partner_contact_address_detailed/i18n/nl.po
odoo_addons/partner_contact_address_detailed/i18n/partner_contact_address_detailed.pot
odoo_addons/partner_contact_address_detailed/i18n/pt_BR.po
odoo_addons/partner_contact_address_detailed/i18n/sl.po
odoo_addons/partner_contact_address_detailed/static/description/icon.png
odoo8_addon_partner_contact_address_detailed-8.0.1.0.0.99.dev11.dist-info/METADATA
odoo8_addon_partner_contact_address_detailed-8.0.1.0.0.99.dev11.dist-info/WHEEL
odoo8_addon_partner_contact_address_detailed-8.0.1.0.0.99.dev11.dist-info/namespace_packages.txt
odoo8_addon_partner_contact_address_detailed-8.0.1.0.0.99.dev11.dist-info/top_level.txt
odoo8_addon_partner_contact_address_detailed-8.0.1.0.0.99.dev11.dist-info/RECORD
